alex_jonesum/__init__.py
alex_jonesum/_jonesum.c
alex_jonesum/_jonesum.cp314-win_amd64.pyd
alex_jonesum/jonesum.c
alex_jonesum/vocabulary.txt
alex_jonesum-2.0.3.dist-info/METADATA
alex_jonesum-2.0.3.dist-info/WHEEL
alex_jonesum-2.0.3.dist-info/top_level.txt
alex_jonesum-2.0.3.dist-info/RECORD
