Metadata-Version: 2.4
Name: alex-jonesum
Version: 2.0.3
Summary: Alex Jones Ipsum generator with C core and Python bindings
Home-page: https://github.com/emboiko/alex_jonesum
Author: Emboiko
Author-email: Emboiko <ed@emboiko.com>
Project-URL: Homepage, https://github.com/emboiko/alex_jonesum
Classifier: Development Status :: 4 - Beta
Classifier: Intended Audience :: Developers
Classifier: License :: OSI Approved :: MIT License
Classifier: Programming Language :: Python :: 3
Classifier: Programming Language :: Python :: 3.6
Classifier: Programming Language :: Python :: 3.7
Classifier: Programming Language :: Python :: 3.8
Classifier: Programming Language :: Python :: 3.9
Classifier: Programming Language :: Python :: 3.10
Classifier: Programming Language :: Python :: 3.11
Classifier: Programming Language :: C
Requires-Python: >=3.6
Dynamic: author
Dynamic: description
Dynamic: description-content-type
Dynamic: home-page
Dynamic: requires-python
